{
  "path": "PCGExFoundations/Public/Elements/PCGExCopyToPoints.h",
  "module": "PCGExFoundations",
  "type": "header",
  "enums": [],
  "structs": [],
  "classes": [
    {
      "name": "UPCGExCopyToPointsSettings",
      "display_name": "Copy to Points",
      "description": "Copy source points to target points, with size-to-fit and justification goodies.",
      "base_class": "UPCGExPointsProcessorSettings",
      "uclass_meta": "MinimalAPI, BlueprintType, ClassGroup = (Procedural), Category=\"PCGEx|Misc\", meta=(PCGExNodeLibraryDoc=\"transform/generate/copy-to-points\")",
      "uproperties": [
        {
          "name": "DataMatching",
          "display_name": "DataMatching",
          "type": "FPCGExMatchingDetails",
          "default": null,
          "overridable": false,
          "instanced": false,
          "show_only_inner": false,
          "edit_condition": null,
          "edit_condition_hides": false,
          "category": null,
          "advanced": false
        },
        {
          "name": "TransformDetails",
          "display_name": "TransformDetails",
          "type": "FPCGExTransformDetails",
          "default": "FPCGExTransformDetails(true, true)",
          "overridable": true,
          "instanced": false,
          "show_only_inner": false,
          "edit_condition": null,
          "edit_condition_hides": false,
          "category": null,
          "advanced": false
        },
        {
          "name": "TargetsAttributesToCopyTags",
          "display_name": "TargetsAttributesToCopyTags",
          "type": "FPCGExAttributeToTagDetails",
          "default": null,
          "overridable": false,
          "instanced": false,
          "show_only_inner": false,
          "edit_condition": null,
          "edit_condition_hides": false,
          "category": "Settings|Tagging & Forwarding",
          "advanced": false
        },
        {
          "name": "TargetsForwarding",
          "display_name": "TargetsForwarding",
          "type": "FPCGExForwardDetails",
          "default": null,
          "overridable": false,
          "instanced": false,
          "show_only_inner": false,
          "edit_condition": null,
          "edit_condition_hides": false,
          "category": "Settings|Tagging & Forwarding",
          "advanced": false
        }
      ],
      "classification": {
        "type": "node_settings",
        "is_abstract": false,
        "is_provider": false,
        "is_consumer": true,
        "is_instanced_factory": false,
        "is_factory_data": false,
        "is_config_struct": false,
        "factory_type": null,
        "consumed_factory_types": [],
        "instanced_properties": []
      },
      "has_point_filter": true,
      "point_filter_label": "PCGExFilters::Labels::SourceFiltersLabel",
      "filter_inputs": [
        {
          "label": "PCGExFilters::Labels::SourceFiltersLabel",
          "tooltip": "Filters",
          "factory_type": "PCGExFactories::PointFilters",
          "required": true
        }
      ],
      "inputs": [
        "Labels"
      ],
      "outputs": [],
      "consumed_factories": [],
      "consumed_filters": [
        {
          "label": "PCGExFilters::Labels::SourceFiltersLabel",
          "tooltip": "Filters",
          "factory_type": "PCGExFactories::PointFilters",
          "required": true
        }
      ],
      "all_properties": [
        {
          "name": "BulkInitData",
          "display_name": "BulkInitData",
          "type": "EPCGExOptionState",
          "default": "EPCGExOptionState::Default",
          "overridable": false,
          "instanced": false,
          "show_only_inner": false,
          "edit_condition": null,
          "edit_condition_hides": false,
          "category": null,
          "advanced": false
        },
        {
          "name": "CacheData",
          "display_name": "CacheData",
          "type": "EPCGExOptionState",
          "default": "EPCGExOptionState::Default",
          "overridable": false,
          "instanced": false,
          "show_only_inner": false,
          "edit_condition": null,
          "edit_condition_hides": false,
          "category": null,
          "advanced": false
        },
        {
          "name": "ScopedAttributeGet",
          "display_name": "ScopedAttributeGet",
          "type": "EPCGExOptionState",
          "default": "EPCGExOptionState::Default",
          "overridable": false,
          "instanced": false,
          "show_only_inner": false,
          "edit_condition": null,
          "edit_condition_hides": false,
          "category": null,
          "advanced": false
        },
        {
          "name": "StealData",
          "display_name": "StealData",
          "type": "EPCGExOptionState",
          "default": "EPCGExOptionState::Disabled",
          "overridable": false,
          "instanced": false,
          "show_only_inner": false,
          "edit_condition": "bCachedSupportsDataStealing",
          "edit_condition_hides": true,
          "category": null,
          "advanced": false
        },
        {
          "name": "ExecutionPolicy",
          "display_name": "ExecutionPolicy",
          "type": "EPCGExExecutionPolicy",
          "default": "EPCGExExecutionPolicy::Default",
          "overridable": false,
          "instanced": false,
          "show_only_inner": false,
          "edit_condition": "bCachedSupportsInitPolicy",
          "edit_condition_hides": false,
          "category": null,
          "advanced": false
        },
        {
          "name": "bFlattenOutput",
          "display_name": "bFlattenOutput",
          "type": "bool",
          "default": "false",
          "overridable": false,
          "instanced": false,
          "show_only_inner": false,
          "edit_condition": null,
          "edit_condition_hides": false,
          "category": "Cleanup",
          "advanced": false
        },
        {
          "name": "bCleanupConsumableAttributes",
          "display_name": "bCleanupConsumableAttributes",
          "type": "bool",
          "default": "false",
          "overridable": false,
          "instanced": false,
          "show_only_inner": false,
          "edit_condition": null,
          "edit_condition_hides": false,
          "category": "Cleanup",
          "advanced": false
        },
        {
          "name": "CommaSeparatedProtectedAttributesName",
          "display_name": "Protected Attributes",
          "type": "FString",
          "default": null,
          "overridable": true,
          "instanced": false,
          "show_only_inner": false,
          "edit_condition": "bCleanupConsumableAttributes",
          "edit_condition_hides": false,
          "category": "Cleanup",
          "advanced": false
        },
        {
          "name": "ProtectedAttributes",
          "display_name": "Protected Attributes",
          "type": "TArray<FName>",
          "default": null,
          "overridable": false,
          "instanced": false,
          "show_only_inner": false,
          "edit_condition": "bCleanupConsumableAttributes",
          "edit_condition_hides": false,
          "category": "Cleanup",
          "advanced": false
        },
        {
          "name": "bPropagateAbortedExecution",
          "display_name": "bPropagateAbortedExecution",
          "type": "bool",
          "default": "false",
          "overridable": false,
          "instanced": false,
          "show_only_inner": false,
          "edit_condition": null,
          "edit_condition_hides": false,
          "category": "Warnings and Errors",
          "advanced": false
        },
        {
          "name": "bQuietInvalidInputWarning",
          "display_name": "bQuietInvalidInputWarning",
          "type": "bool",
          "default": "false",
          "overridable": false,
          "instanced": false,
          "show_only_inner": false,
          "edit_condition": null,
          "edit_condition_hides": false,
          "category": "Warnings and Errors",
          "advanced": false
        },
        {
          "name": "bQuietMissingInputError",
          "display_name": "bQuietMissingInputError",
          "type": "bool",
          "default": "false",
          "overridable": false,
          "instanced": false,
          "show_only_inner": false,
          "edit_condition": null,
          "edit_condition_hides": false,
          "category": "Warnings and Errors",
          "advanced": false
        },
        {
          "name": "bQuietCancellationError",
          "display_name": "bQuietCancellationError",
          "type": "bool",
          "default": "false",
          "overridable": false,
          "instanced": false,
          "show_only_inner": false,
          "edit_condition": null,
          "edit_condition_hides": false,
          "category": "Warnings and Errors",
          "advanced": false
        },
        {
          "name": "DataMatching",
          "display_name": "DataMatching",
          "type": "FPCGExMatchingDetails",
          "default": null,
          "overridable": false,
          "instanced": false,
          "show_only_inner": false,
          "edit_condition": null,
          "edit_condition_hides": false,
          "category": null,
          "advanced": false
        },
        {
          "name": "TransformDetails",
          "display_name": "TransformDetails",
          "type": "FPCGExTransformDetails",
          "default": "FPCGExTransformDetails(true, true)",
          "overridable": true,
          "instanced": false,
          "show_only_inner": false,
          "edit_condition": null,
          "edit_condition_hides": false,
          "category": null,
          "advanced": false
        },
        {
          "name": "TargetsAttributesToCopyTags",
          "display_name": "TargetsAttributesToCopyTags",
          "type": "FPCGExAttributeToTagDetails",
          "default": null,
          "overridable": false,
          "instanced": false,
          "show_only_inner": false,
          "edit_condition": null,
          "edit_condition_hides": false,
          "category": "Settings|Tagging & Forwarding",
          "advanced": false
        },
        {
          "name": "TargetsForwarding",
          "display_name": "TargetsForwarding",
          "type": "FPCGExForwardDetails",
          "default": null,
          "overridable": false,
          "instanced": false,
          "show_only_inner": false,
          "edit_condition": null,
          "edit_condition_hides": false,
          "category": "Settings|Tagging & Forwarding",
          "advanced": false
        }
      ]
    }
  ],
  "operations": [
    {
      "name": "FPCGExCopyToPointsElement",
      "base_class": "FPCGExPointsProcessorElement"
    }
  ],
  "namespaces": {}
}