{
  "path": "PCGExElementsValencyEditor/Public/Cages/PCGExValencyAssetPalette.h",
  "module": "PCGExElementsValencyEditor",
  "type": "header",
  "enums": [],
  "structs": [],
  "classes": [
    {
      "name": "APCGExValencyAssetPalette",
      "display_name": "APCGExValencyAssetPalette",
      "description": "",
      "base_class": "AActor",
      "uclass_meta": "HideCategories = (Rendering, Replication, Collision, HLOD, Physics, Networking, Input, LOD, Cooking)",
      "uproperties": [
        {
          "name": "PaletteName",
          "display_name": "PaletteName",
          "type": "FString",
          "default": null,
          "overridable": false,
          "instanced": false,
          "show_only_inner": false,
          "edit_condition": null,
          "edit_condition_hides": false,
          "category": "Palette",
          "advanced": false
        },
        {
          "name": "PaletteColor",
          "display_name": "PaletteColor",
          "type": "FLinearColor",
          "default": "FLinearColor(0.8f, 0.5f, 0.2f, 0.5f)",
          "overridable": false,
          "instanced": false,
          "show_only_inner": false,
          "edit_condition": null,
          "edit_condition_hides": false,
          "category": "Palette",
          "advanced": false
        },
        {
          "name": "ManualAssetEntries",
          "display_name": "ManualAssetEntries",
          "type": "TArray<FPCGExValencyAssetEntry>",
          "default": null,
          "overridable": false,
          "instanced": false,
          "show_only_inner": false,
          "edit_condition": null,
          "edit_condition_hides": false,
          "category": "Palette|Assets",
          "advanced": false
        },
        {
          "name": "ScannedAssetEntries",
          "display_name": "ScannedAssetEntries",
          "type": "TArray<FPCGExValencyAssetEntry>",
          "default": null,
          "overridable": false,
          "instanced": false,
          "show_only_inner": false,
          "edit_condition": null,
          "edit_condition_hides": false,
          "category": "Palette|Assets",
          "advanced": false
        },
        {
          "name": "DetectionExtent",
          "display_name": "DetectionExtent",
          "type": "FVector",
          "default": "FVector(100.0f)",
          "overridable": false,
          "instanced": false,
          "show_only_inner": false,
          "edit_condition": null,
          "edit_condition_hides": false,
          "category": "Palette|Detection",
          "advanced": false
        },
        {
          "name": "bAutoRegisterContainedAssets",
          "display_name": "bAutoRegisterContainedAssets",
          "type": "bool",
          "default": "true",
          "overridable": false,
          "instanced": false,
          "show_only_inner": false,
          "edit_condition": null,
          "edit_condition_hides": false,
          "category": "Palette|Detection",
          "advanced": false
        },
        {
          "name": "bPreserveLocalTransforms",
          "display_name": "bPreserveLocalTransforms",
          "type": "bool",
          "default": "false",
          "overridable": false,
          "instanced": false,
          "show_only_inner": false,
          "edit_condition": null,
          "edit_condition_hides": false,
          "category": "Palette|Detection",
          "advanced": false
        },
        {
          "name": "LocalTransformFlags",
          "display_name": "LocalTransformFlags",
          "type": "uint8",
          "default": "static_cast<uint8>(EPCGExLocalTransformFlags::All)",
          "overridable": false,
          "instanced": false,
          "show_only_inner": false,
          "edit_condition": "bPreserveLocalTransforms",
          "edit_condition_hides": false,
          "category": "Palette|Detection",
          "advanced": false
        },
        {
          "name": "ModuleSettings",
          "display_name": "ModuleSettings",
          "type": "FPCGExValencyModuleSettings",
          "default": null,
          "overridable": false,
          "instanced": false,
          "show_only_inner": false,
          "edit_condition": null,
          "edit_condition_hides": false,
          "category": "Palette|Module",
          "advanced": false
        },
        {
          "name": "BoxComponent",
          "display_name": "BoxComponent",
          "type": "TObjectPtr<UBoxComponent>",
          "default": null,
          "overridable": false,
          "instanced": false,
          "show_only_inner": false,
          "edit_condition": null,
          "edit_condition_hides": false,
          "category": "Palette|Detection",
          "advanced": false
        },
        {
          "name": "bNeedsInitialScan",
          "display_name": "bNeedsInitialScan",
          "type": "bool",
          "default": "true",
          "overridable": false,
          "instanced": false,
          "show_only_inner": false,
          "edit_condition": null,
          "edit_condition_hides": false,
          "category": null,
          "advanced": false
        }
      ],
      "classification": {
        "type": "unknown",
        "is_abstract": false,
        "is_provider": false,
        "is_consumer": false,
        "is_instanced_factory": false,
        "is_factory_data": false,
        "is_config_struct": false,
        "factory_type": null,
        "consumed_factory_types": [],
        "instanced_properties": []
      },
      "has_point_filter": false,
      "point_filter_label": null,
      "filter_inputs": [],
      "inputs": [],
      "outputs": [],
      "consumed_factories": [],
      "consumed_filters": [],
      "all_properties": [
        {
          "name": "PaletteName",
          "display_name": "PaletteName",
          "type": "FString",
          "default": null,
          "overridable": false,
          "instanced": false,
          "show_only_inner": false,
          "edit_condition": null,
          "edit_condition_hides": false,
          "category": "Palette",
          "advanced": false
        },
        {
          "name": "PaletteColor",
          "display_name": "PaletteColor",
          "type": "FLinearColor",
          "default": "FLinearColor(0.8f, 0.5f, 0.2f, 0.5f)",
          "overridable": false,
          "instanced": false,
          "show_only_inner": false,
          "edit_condition": null,
          "edit_condition_hides": false,
          "category": "Palette",
          "advanced": false
        },
        {
          "name": "ManualAssetEntries",
          "display_name": "ManualAssetEntries",
          "type": "TArray<FPCGExValencyAssetEntry>",
          "default": null,
          "overridable": false,
          "instanced": false,
          "show_only_inner": false,
          "edit_condition": null,
          "edit_condition_hides": false,
          "category": "Palette|Assets",
          "advanced": false
        },
        {
          "name": "ScannedAssetEntries",
          "display_name": "ScannedAssetEntries",
          "type": "TArray<FPCGExValencyAssetEntry>",
          "default": null,
          "overridable": false,
          "instanced": false,
          "show_only_inner": false,
          "edit_condition": null,
          "edit_condition_hides": false,
          "category": "Palette|Assets",
          "advanced": false
        },
        {
          "name": "DetectionExtent",
          "display_name": "DetectionExtent",
          "type": "FVector",
          "default": "FVector(100.0f)",
          "overridable": false,
          "instanced": false,
          "show_only_inner": false,
          "edit_condition": null,
          "edit_condition_hides": false,
          "category": "Palette|Detection",
          "advanced": false
        },
        {
          "name": "bAutoRegisterContainedAssets",
          "display_name": "bAutoRegisterContainedAssets",
          "type": "bool",
          "default": "true",
          "overridable": false,
          "instanced": false,
          "show_only_inner": false,
          "edit_condition": null,
          "edit_condition_hides": false,
          "category": "Palette|Detection",
          "advanced": false
        },
        {
          "name": "bPreserveLocalTransforms",
          "display_name": "bPreserveLocalTransforms",
          "type": "bool",
          "default": "false",
          "overridable": false,
          "instanced": false,
          "show_only_inner": false,
          "edit_condition": null,
          "edit_condition_hides": false,
          "category": "Palette|Detection",
          "advanced": false
        },
        {
          "name": "LocalTransformFlags",
          "display_name": "LocalTransformFlags",
          "type": "uint8",
          "default": "static_cast<uint8>(EPCGExLocalTransformFlags::All)",
          "overridable": false,
          "instanced": false,
          "show_only_inner": false,
          "edit_condition": "bPreserveLocalTransforms",
          "edit_condition_hides": false,
          "category": "Palette|Detection",
          "advanced": false
        },
        {
          "name": "ModuleSettings",
          "display_name": "ModuleSettings",
          "type": "FPCGExValencyModuleSettings",
          "default": null,
          "overridable": false,
          "instanced": false,
          "show_only_inner": false,
          "edit_condition": null,
          "edit_condition_hides": false,
          "category": "Palette|Module",
          "advanced": false
        },
        {
          "name": "BoxComponent",
          "display_name": "BoxComponent",
          "type": "TObjectPtr<UBoxComponent>",
          "default": null,
          "overridable": false,
          "instanced": false,
          "show_only_inner": false,
          "edit_condition": null,
          "edit_condition_hides": false,
          "category": "Palette|Detection",
          "advanced": false
        },
        {
          "name": "bNeedsInitialScan",
          "display_name": "bNeedsInitialScan",
          "type": "bool",
          "default": "true",
          "overridable": false,
          "instanced": false,
          "show_only_inner": false,
          "edit_condition": null,
          "edit_condition_hides": false,
          "category": null,
          "advanced": false
        }
      ]
    }
  ],
  "operations": [],
  "namespaces": {}
}